cluster_flag-0.1.2.dist-info/DESCRIPTION.rst
cluster_flag-0.1.2.dist-info/METADATA
cluster_flag-0.1.2.dist-info/RECORD
cluster_flag-0.1.2.dist-info/WHEEL
cluster_flag-0.1.2.dist-info/metadata.json
cluster_flag-0.1.2.dist-info/top_level.txt
clusterflag/__init__.py
clusterflag/country_flags.py
