Metadata-Version: 2.0
Name: cluster-flag
Version: 0.1.2
Summary: Generate country flags with numpy and pandas
Home-page: https://github.com/dashee87/cluster-flag
Author: David Sheehan
Author-email: davidfsheehan87@gamil.com
License: MIT
Keywords: country flag numpy pandas
Platform: UNKNOWN
Classifier: Development Status :: 3 - Alpha
Classifier: License :: OSI Approved :: MIT License
Classifier: Programming Language :: Python
Classifier: Programming Language :: Python :: 3
Classifier: Programming Language :: Python :: 3.4
Classifier: Programming Language :: Python :: 3.5
Classifier: Programming Language :: Python :: 3.6
Classifier: Operating System :: OS Independent
Classifier: Intended Audience :: Science/Research
Classifier: Intended Audience :: Developers
Classifier: Intended Audience :: Education
Classifier: Topic :: Scientific/Engineering :: Visualization
Requires-Dist: numpy (>=1.11.0)
Requires-Dist: pandas (>=0.17.1)
